setup.py
sk_import/__init__.py
sk_import/main.py
sk_import.egg-info/PKG-INFO
sk_import.egg-info/SOURCES.txt
sk_import.egg-info/dependency_links.txt
sk_import.egg-info/entry_points.txt
sk_import.egg-info/not-zip-safe
sk_import.egg-info/requires.txt
sk_import.egg-info/top_level.txt