Metadata-Version: 1.1
Name: sk-import
Version: 0.2
Summary: Bypass Songkick's import hard limit by hitting the site directly
Home-page: http://github.com/rattboi/sk-import/
Author: rattboi
Author-email: rattboi@gmail.com
License: UNKNOWN
Platform: UNKNOWN
Classifier: Development Status :: 4 - Beta
Classifier: Operating System :: POSIX :: Linux
Classifier: Programming Language :: Python :: 3.3
